README.md
setup.cfg
setup.py
wine_wrap/__init__.py
wine_wrap/fs_handler.py
wine_wrap/main.py
wine_wrap/prefix_handler.py
wine_wrap/utils.py
wine_wrap/wine_wrapper.py
wine_wrap.egg-info/PKG-INFO
wine_wrap.egg-info/SOURCES.txt
wine_wrap.egg-info/dependency_links.txt
wine_wrap.egg-info/entry_points.txt
wine_wrap.egg-info/requires.txt
wine_wrap.egg-info/top_level.txt