Metadata-Version: 1.1
Name: wine-wrap
Version: 0.1.0
Summary: A versioned wine-prefix management tool
Home-page: https://github.com/kpj/wine_wrap
Author: kpj
Author-email: kpjkpjkpjkpjkpjkpj@gmail.com
License: MIT
Keywords: wine_wrap wine windows
Platform: UNKNOWN
Classifier: Development Status :: 3 - Alpha
Classifier: Intended Audience :: End Users/Desktop
Classifier: Topic :: System :: Systems Administration
Classifier: License :: OSI Approved :: MIT License
Classifier: Programming Language :: Python :: 3 :: Only
